MANIFEST.in
README
setup.py
flexipy/__init__.py
flexipy/adresar.py
flexipy/api.py
flexipy/bank.py
flexipy/config.py
flexipy/demo_flexibee.conf
flexipy/exceptions.py
flexipy/faktura.py
flexipy/flexipy.conf
flexipy/main.py
flexipy/pokladna.py
flexipy/test_flexipy.conf
flexipy.egg-info/PKG-INFO
flexipy.egg-info/SOURCES.txt
flexipy.egg-info/dependency_links.txt
flexipy.egg-info/requires.txt
flexipy.egg-info/top_level.txt