Metadata-Version: 1.1
Name: flexipy
Version: 0.4.2
Summary: A library for communication with accounting system Flexibee.
Home-page: https://github.com/JakubJecminek/flexipy
Author: Jakub Jecminek
Author-email: jecmijak@gmail.com
License: BSD
Keywords: flexibee accounting invoices
Platform: UNKNOWN
Classifier: Development Status :: 3 - Alpha
Classifier: Intended Audience :: Developers
Classifier: Operating System :: OS Independent
Classifier: Programming Language :: Python :: 2
